simple_github/__init__.py
simple_github/auth.py
simple_github/client.py
simple_github-2.2.1.dist-info/METADATA
simple_github-2.2.1.dist-info/WHEEL
simple_github-2.2.1.dist-info/licenses/LICENSE
simple_github-2.2.1.dist-info/RECORD
