Metadata-Version: 2.4
Name: simple-github
Version: 2.2.1
Summary: A simple Github client that only provides auth and access to the REST and GraphQL APIs.
Author-email: Mozilla Release Engineering <release+simple-github@mozilla.com>
License-Expression: MPL-2.0
License-File: LICENSE
Classifier: Development Status :: 5 - Production/Stable
Classifier: License :: OSI Approved :: Mozilla Public License 2.0 (MPL 2.0)
Classifier: Programming Language :: Python :: 3.8
Classifier: Programming Language :: Python :: 3.9
Classifier: Programming Language :: Python :: 3.10
Classifier: Programming Language :: Python :: 3.11
Classifier: Programming Language :: Python :: 3.12
Classifier: Topic :: Software Development
Requires-Python: >=3.8
Requires-Dist: aiohttp[speedups]~=3.8
Requires-Dist: gql[aiohttp,requests]<4,>=3.5.1
Requires-Dist: pyjwt[crypto]~=2.8
Requires-Dist: requests~=2.31
